brandfolder/__init__.py
brandfolder/asset.py
brandfolder/attachment.py
brandfolder/brandfolder.py
brandfolder/client.py
brandfolder/collection.py
brandfolder/organization.py
brandfolder/resource.py
brandfolder/resource_container.py
brandfolder/section.py
brandfolder-2.0.0.dist-info/LICENSE.txt
brandfolder-2.0.0.dist-info/METADATA
brandfolder-2.0.0.dist-info/WHEEL
brandfolder-2.0.0.dist-info/top_level.txt
brandfolder-2.0.0.dist-info/RECORD
