Metadata-Version: 2.1
Name: brandfolder
Version: 2.0.0
Summary: A simple wrapper for the Brandfolder API
Home-page: https://github.com/brandfolder/brandfolder-sdk-python
Author: Brandfolder
Author-email: developers@brandfolder.com
License: UNKNOWN
Platform: UNKNOWN
Classifier: Programming Language :: Python :: 3
Classifier: License :: OSI Approved :: MIT License
Classifier: Operating System :: OS Independent
License-File: LICENSE.txt
Requires-Dist: requests (>=2)
